{
  "routing_engine_result": {
    "routes": [
      {
        "vehicle_name": "Refrigerated Truck",
        "route_index": [
          0,
          1,
          2
        ],
        "route_name": [
          "Cold Storage Facility",
          "Restaurant A",
          "Restaurant B"
        ],
        "route_cost_details": {
          "objective_cost": 118262,
          "distance_cost": 58981,
          "duration_cost": 5310,
          "fixed_cost": 300
        }
      }
    ],
    "unassigned_visit_indices": [],
    "unassigned_visit_names": [],
    "solution_cost_details": {
      "total_objective_cost": 118262,
      "total_distance_cost": 58981,
      "total_duration_cost": 5310,
      "max_distance_cost": 58981,
      "max_duration_cost": 5310,
      "total_fixed_cost": 0,
      "unassigned_penalty_cost": 0
    }
  },
  "status": "feasible",
  "detail": "Successfully processed",
  "job_id": "472d6330565b40e88c18cdea993edf9c"
}
