<?xml version="1.0" encoding="utf-8" ?>
<!-- Copyright 2022 OpenSynergy Indonesia
     Copyright 2022 Simetri Sinergi
     License AGPL-3.0 or later (http://www.gnu.org/licenses/agpl). -->
<odoo>
<data noupdate="1">
<record id="journal1" model="account.journal">
    <field name="name">Employee Cash Advance</field>
    <field name="code">CA</field>
    <field name="type">general</field>
</record>

<record id="journal2" model="account.journal">
    <field name="name">Employee Cash Advance Settlement</field>
    <field name="code">CAS</field>
    <field name="type">general</field>
</record>
</data>
</odoo>
