{
    "Afghan Jews": "تصنيف:أفغان يهود",
    "African Jews": "تصنيف:أفارقة يهود",
    "African-American Jews": "تصنيف:أمريكيون أفارقة يهود",
    "Algerian Jews": "تصنيف:جزائريون يهود",
    "American Jews": "تصنيف:أمريكيون يهود",
    "Arab Jews": "تصنيف:عرب يهود",
    "Arabian Jews": "تصنيف:عرب يهود",
    "Argentine Jews": "تصنيف:أرجنتينيون يهود",
    "Armenian Jews": "تصنيف:أرمن يهود",
    "Aruban Jews": "تصنيف:أروبيون يهود",
    "Asian Jews": "تصنيف:آسيويون يهود",
    "Assyrian Jews": "تصنيف:آشوريون يهود",
    "Australian Jews": "تصنيف:أستراليون يهود",
    "Austrian Jews": "تصنيف:نمساويون يهود",
    "Azerbaijani Jews": "تصنيف:أذربيجانيون يهود",
    "Bahraini Jews": "تصنيف:بحرينيون يهود",
    "Barbadian Jews": "تصنيف:بربادوسيون يهود",
    "Belarusian Jews": "تصنيف:بيلاروسيون يهود",
    "Belgian Jews": "تصنيف:بلجيكيون يهود",
    "Belizean Jews": "تصنيف:بليزيون يهود",
    "Bolivian Jews": "تصنيف:بوليفيون يهود",
    "Bosnia and Herzegovina Jews": "تصنيف:بوسنيون يهود",
    "Brazilian Jews": "تصنيف:برازيليون يهود",
    "British Jews": "تصنيف:بريطانيون يهود",
    "Bulgarian Jews": "تصنيف:بلغاريون يهود",
    "Burmese Jews": "تصنيف:بورميون يهود",
    "Byzantine Jews": "تصنيف:بيزنطيون يهود",
    "Canadian Jews": "تصنيف:كنديون يهود",
    "Cape Verdean Jews": "تصنيف:أخضريون يهود",
    "Caribbean Jews": "تصنيف:كاريبيون يهود",
    "Central Asian Jews": "تصنيف:آسيويون أوسطيون يهود",
    "Chilean Jews": "تصنيف:تشيليون يهود",
    "Chinese Jews": "تصنيف:صينيون يهود",
    "Colombian Jews": "تصنيف:كولومبيون يهود",
    "Costa Rican Jews": "تصنيف:كوستاريكيون يهود",
    "Crimean Jews": "تصنيف:قرم يهود",
    "Croatian Jews": "تصنيف:كروات يهود",
    "Cuban Jews": "تصنيف:كوبيون يهود",
    "Cypriot Jews": "تصنيف:قبرصيون يهود",
    "Czech Jews": "تصنيف:تشيكيون يهود",
    "Czechoslovak Jews": "تصنيف:تشيكوسلوفاكيون يهود",
    "Danish Jews": "تصنيف:دنماركيون يهود",
    "Democratic Republic of Congo Jews": "تصنيف:كونغويون ديمقراطيون يهود",
    "Dutch Jews": "تصنيف:هولنديون يهود",
    "Ecuadorian Jews": "تصنيف:إكوادوريون يهود",
    "Egyptian Jews": "تصنيف:مصريون يهود",
    "English Jews": "تصنيف:إنجليز يهود",
    "Estonian Jews": "تصنيف:إستونيون يهود",
    "Ethiopian Jews": "تصنيف:إثيوبيون يهود",
    "European Jews": "تصنيف:أوروبيون يهود",
    "Fijian Jews": "تصنيف:فيجيون يهود",
    "Finnish Jews": "تصنيف:فنلنديون يهود",
    "French Guianan Jews": "تصنيف:غويانيون فرنسيون يهود",
    "French Jews": "تصنيف:فرنسيون يهود",
    "Georgian Jews": "تصنيف:جورجيون يهود",
    "German Jews": "تصنيف:ألمان يهود",
    "Ghanaian Jews": "تصنيف:غانيون يهود",
    "Gibraltarian Jews": "تصنيف:جبل طارقيون يهود",
    "Greek Jews": "تصنيف:يونانيون يهود",
    "Guamanian Jews": "تصنيف:غواميون يهود",
    "Guatemalan Jews": "تصنيف:غواتيماليون يهود",
    "Guyanese Jews": "تصنيف:غيانيون يهود",
    "Haitian Jews": "تصنيف:هايتيون يهود",
    "Honduran Jews": "تصنيف:هندوراسيون يهود",
    "Hong Kong Jews": "تصنيف:هونغ كونغيون يهود",
    "Hungarian Jews": "تصنيف:مجريون يهود",
    "Icelandic Jews": "تصنيف:آيسلنديون يهود",
    "Indian Jews": "تصنيف:هنود يهود",
    "Indonesian Jews": "تصنيف:إندونيسيون يهود",
    "Iranian Jews": "تصنيف:إيرانيون يهود",
    "Iraqi Jews": "تصنيف:عراقيون يهود",
    "Irish Jews": "تصنيف:أيرلنديون يهود",
    "Israeli Jews": "تصنيف:إسرائيليون يهود",
    "Italian Jews": "تصنيف:إيطاليون يهود",
    "Jamaican Jews": "تصنيف:جامايكيون يهود",
    "Japanese Jews": "تصنيف:يابانيون يهود",
    "Kazakhstani Jews": "تصنيف:كازاخستانيون يهود",
    "Kenyan Jews": "تصنيف:كينيون يهود",
    "Kurdish Jews": "تصنيف:أكراد يهود",
    "Kuwaiti Jews": "تصنيف:كويتيون يهود",
    "Kyrgyzstani Jews": "تصنيف:قيرغيزستانيون يهود",
    "Latvian Jews": "تصنيف:لاتفيون يهود",
    "Lebanese Jews": "تصنيف:لبنانيون يهود",
    "Libyan Jews": "تصنيف:ليبيون يهود",
    "Lithuanian Jews": "تصنيف:ليتوانيون يهود",
    "Luxembourgian Jews": "تصنيف:لوكسمبورغيون يهود",
    "Macedonian Jews": "تصنيف:مقدونيون يهود",
    "Malian Jews": "تصنيف:ماليون يهود",
    "Mauritian Jews": "تصنيف:موريشيوسيون يهود",
    "Mexican Jews": "تصنيف:مكسيكيون يهود",
    "Middle Eastern Jews": "تصنيف:شرقيون أوسطيون يهود",
    "Moldovan Jews": "تصنيف:مولدوفيون يهود",
    "Montenegrin Jews": "تصنيف:مونتينيغريون يهود",
    "Moravian Jews": "تصنيف:مورافيون يهود",
    "Moroccan Jews": "تصنيف:مغاربة يهود",
    "Namibian Jews": "تصنيف:ناميبيون يهود",
    "Nicaraguan Jews": "تصنيف:نيكاراغويون يهود",
    "Nigerian Jews": "تصنيف:نيجيريون يهود",
    "North American Jews": "تصنيف:أمريكيون شماليون يهود",
    "Norwegian Jews": "تصنيف:نرويجيون يهود",
    "Oceanian Jews": "تصنيف:أوقيانوسيون يهود",
    "Palestinian Jews": "تصنيف:فلسطينيون يهود",
    "Panamanian Jews": "تصنيف:بنميون يهود",
    "Paraguayan Jews": "تصنيف:بارغوايانيون يهود",
    "Peruvian Jews": "تصنيف:بيرويون يهود",
    "Polish Jews": "تصنيف:بولنديون يهود",
    "Portuguese Jews": "تصنيف:برتغاليون يهود",
    "Puerto Rican Jews": "تصنيف:بورتوريكيون يهود",
    "Rhodesian Jews": "تصنيف:رودوسيون يهود",
    "Romanian Jews": "تصنيف:رومان يهود",
    "Russian Jews": "تصنيف:روس يهود",
    "Salvadoran Jews": "تصنيف:سلفادوريون يهود",
    "Samoan Jews": "تصنيف:سامويون يهود",
    "Scottish Jews": "تصنيف:إسكتلنديون يهود",
    "Serbian Jews": "تصنيف:صرب يهود",
    "Singaporean Jews": "تصنيف:سنغافوريون يهود",
    "Slovak Jews": "تصنيف:سلوفاكيون يهود",
    "Slovenian Jews": "تصنيف:سلوفينيون يهود",
    "South American Jews": "تصنيف:أمريكيون جنوبيون يهود",
    "Southeast Asian Jews": "تصنيف:آسيويون جنوبيون شرقيون يهود",
    "Soviet Jews": "تصنيف:سوفيت يهود",
    "Spanish Jews": "تصنيف:إسبان يهود",
    "Sri Lankan Jews": "تصنيف:سريلانكيون يهود",
    "Sudanese Jews": "تصنيف:سودانيون يهود",
    "Surinamese Jews": "تصنيف:سوريناميون يهود",
    "Swazi Jews": "تصنيف:سوازيلنديون يهود",
    "Swedish Jews": "تصنيف:سويديون يهود",
    "Swiss Jews": "تصنيف:سويسريون يهود",
    "Syrian Jews": "تصنيف:سوريون يهود",
    "Taiwanese Jews": "تصنيف:تايوانيون يهود",
    "Tajikistani Jews": "تصنيف:طاجيك يهود",
    "Tunisian Jews": "تصنيف:تونسيون يهود",
    "Turkish Jews": "تصنيف:أتراك يهود",
    "Turkmenistan Jews": "تصنيف:تركمانيون يهود",
    "Ugandan Jews": "تصنيف:أوغنديون يهود",
    "Ukrainian Jews": "تصنيف:أوكرانيون يهود",
    "Uruguayan Jews": "تصنيف:أوروغويانيون يهود",
    "Uzbekistani Jews": "تصنيف:أوزبكستانيون يهود",
    "Venezuelan Jews": "تصنيف:فنزويليون يهود",
    "Welsh Jews": "تصنيف:ويلزيون يهود",
    "Yemenite Jews": "تصنيف:يمنيون يهود",
    "Yugoslav Jews": "تصنيف:يوغسلافيون يهود",
    "Zambian Jews": "تصنيف:زامبيون يهود",
    "Zimbabwean Jews": "تصنيف:زيمبابويون يهود",
    "Jewish American players of American football": "تصنيف:لاعبو كرة قدم أمريكية أمريكيون يهود",
    "Jewish American referees and umpires": "تصنيف:حكام رياضات أمريكيون يهود",
    "Jewish American sports announcers": "تصنيف:مذيعو رياضية أمريكيون يهود",
    "Jewish American sports coaches": "تصنيف:مدربو رياضة أمريكيون يهود",
    "Jewish American tennis players": "تصنيف:لاعبو كرة مضرب أمريكيون يهود"
}
