{
    "AppName": "cosmicfrog",
    "SchemaName": "anura",
    "SchemaVersion": "v0.2",
    "TableName": "CustomSimulationScripts",
    "fields": [
        {
            "Column Name": "CustomScriptName",
            "Data Type": "Name",
            "Validation Type": "",
            "Required": "Yes",
            "RequiredIf": "",
            "PK": "Yes",
            "Master Table": "",
            "Expandable": "Yes",
            "Technology": "[THROG, DENDRO]",
            "AllowableUOMTypes": "",
            "Relates to keys": "",
            "Default value": "",
            "Notes": "",
            "Explanation": "The name of the custom script. Depending on the Script Policy Type, this name can be entered into the SIM Policy field of the Transportation, Production, Inventory, Customer Fulfillment, Replenishment or Procurement Policy tables.",
            "PrecisionCategory": "[NaN]",
            "BasicMode": "[]",
            "MasterColumn": ""
        },
        {
            "Column Name": "CustomScriptPolicyType",
            "Data Type": "[Inventory, Sourcing, Transportation, Production, OnModelStart, RecurringEvent]",
            "Validation Type": "",
            "Required": "Yes",
            "RequiredIf": "",
            "PK": "",
            "Master Table": "",
            "Expandable": "Yes",
            "Technology": "[THROG, DENDRO]",
            "AllowableUOMTypes": "",
            "Relates to keys": "",
            "Default value": "",
            "Notes": "",
            "Explanation": "The type of policy the script has been built to enforce. If the policy is set to Transportation, Production, Inventory or Sourcing then the Script Name must be referenced in the corresponding Policy table. If the Policy Type is set to be On Model Start, it will execute at the beginning of the model. If the Policy Type is set to Recurring Event it will begin on the entered Start Date, will be repeatedly executed based on the Time Between Events, and then will stop on the End Date.",
            "PrecisionCategory": "[NaN]",
            "BasicMode": "[]",
            "MasterColumn": ""
        },
        {
            "Column Name": "ExecutablePath",
            "Data Type": "String",
            "Validation Type": "",
            "Required": "Yes",
            "RequiredIf": "",
            "PK": "",
            "Master Table": "",
            "Expandable": "",
            "Technology": "[THROG, DENDRO]",
            "AllowableUOMTypes": "",
            "Relates to keys": "",
            "Default value": "",
            "Notes": "",
            "Explanation": "The path to where the python file is saved.",
            "PrecisionCategory": "[NaN]",
            "BasicMode": "[]",
            "MasterColumn": ""
        },
        {
            "Column Name": "StartDate",
            "Data Type": "Date/Time*",
            "Validation Type": "",
            "Required": "",
            "RequiredIf": "",
            "PK": "",
            "Master Table": "",
            "Expandable": "",
            "Technology": "[]",
            "AllowableUOMTypes": "",
            "Relates to keys": "",
            "Default value": "",
            "Notes": "",
            "Explanation": "For a Policy Type of Recurring Event, the Start Date will specify the first point in the simulation at which the script will execute.",
            "PrecisionCategory": "[NaN]",
            "BasicMode": "[]",
            "MasterColumn": ""
        },
        {
            "Column Name": "TimeBetweenEvents",
            "Data Type": "double",
            "Validation Type": "",
            "Required": "",
            "RequiredIf": "",
            "PK": "",
            "Master Table": "",
            "Expandable": "",
            "Technology": "[]",
            "AllowableUOMTypes": "",
            "Relates to keys": "",
            "Default value": "",
            "Notes": "",
            "Explanation": "For a Policy Type of Recurring Event, the Time Between Events will specify how the interval at which the policy will be evaluated.",
            "PrecisionCategory": "[Time]",
            "BasicMode": "[]",
            "MasterColumn": ""
        },
        {
            "Column Name": "TimeBetweenEventsUOM",
            "Data Type": "Name",
            "Validation Type": "ExistsInMasterTable",
            "Required": "",
            "RequiredIf": "",
            "PK": "",
            "Master Table": "",
            "Expandable": "",
            "Technology": "[]",
            "AllowableUOMTypes": "",
            "Relates to keys": "",
            "Default value": "",
            "Notes": "",
            "Explanation": "The unit of measure that time is evaluated in.",
            "PrecisionCategory": "[NaN]",
            "BasicMode": "[]",
            "MasterColumn": "Symbol"
        },
        {
            "Column Name": "EndDate",
            "Data Type": "Date/Time*",
            "Validation Type": "",
            "Required": "",
            "RequiredIf": "",
            "PK": "",
            "Master Table": "",
            "Expandable": "",
            "Technology": "[]",
            "AllowableUOMTypes": "",
            "Relates to keys": "",
            "Default value": "",
            "Notes": "",
            "Explanation": "For a Policy Type of Recurring Event, the End Date will specify the last point in the simulation at which the script will execute.",
            "PrecisionCategory": "[NaN]",
            "BasicMode": "[]",
            "MasterColumn": ""
        },
        {
            "Column Name": "Notes",
            "Data Type": "String",
            "Validation Type": "",
            "Required": "",
            "RequiredIf": "",
            "PK": "",
            "Master Table": "",
            "Expandable": "",
            "Technology": "[THROG, DENDRO]",
            "AllowableUOMTypes": "",
            "Relates to keys": "",
            "Default value": "",
            "Notes": "",
            "Explanation": "",
            "PrecisionCategory": "[NaN]",
            "BasicMode": "[]",
            "MasterColumn": ""
        }
    ]
}