{
    "header": "Resumo da Operação",
    "widgets": [
        {
            "columns": {
                "columnItems": [
                    {
                        "widgets": [
                            {
                                "decoratedText": {
                                    "topLabel": "Duração",
                                    "text": "⏱️ {}"
                                }
                            }
                        ]
                    },
                    {
                        "widgets": [
                            {
                                "decoratedText": {
                                    "topLabel": "Sucesso",
                                    "text": "🎯 {}"
                                }
                            }
                        ]
                    }
                ]
            }
        }
    ]
}