{
    "member_sets": [
        {
            "id": 1,
            "l_y": null,
            "l_z": null,
            "classification": null,
            "members": [
                {
                    "id": 5,
                    "start_node": {
                        "id": 7,
                        "classification": "",
                        "X": 0.0,
                        "Y": 0.1,
                        "Z": -0.1,
                        "nodal_support": null
                    },
                    "end_node": {
                        "id": 6,
                        "classification": "",
                        "X": 0.0,
                        "Y": 0.1,
                        "Z": 0.0,
                        "nodal_support": 1
                    },
                    "section": 1,
                    "rotation_angle": 0.0,
                    "start_hinge": null,
                    "end_hinge": null,
                    "classification": "",
                    "weight": 2.222404890174144,
                    "chi": null,
                    "reference_member": null,
                    "reference_node": null,
                    "member_type": "Normal"
                },
                {
                    "id": 6,
                    "start_node": {
                        "id": 6,
                        "classification": "",
                        "X": 0.0,
                        "Y": 0.1,
                        "Z": 0.0,
                        "nodal_support": 1
                    },
                    "end_node": {
                        "id": 9,
                        "classification": "",
                        "X": 0.0,
                        "Y": 0.1,
                        "Z": 0.1,
                        "nodal_support": null
                    },
                    "section": 1,
                    "rotation_angle": 0.0,
                    "start_hinge": null,
                    "end_hinge": null,
                    "classification": "",
                    "weight": 2.222404890174144,
                    "chi": null,
                    "reference_member": null,
                    "reference_node": null,
                    "member_type": "Normal"
                },
                {
                    "id": 7,
                    "start_node": {
                        "id": 9,
                        "classification": "",
                        "X": 0.0,
                        "Y": 0.1,
                        "Z": 0.1,
                        "nodal_support": null
                    },
                    "end_node": {
                        "id": 8,
                        "classification": "",
                        "X": 0.0,
                        "Y": 0.1,
                        "Z": 1.3,
                        "nodal_support": 1
                    },
                    "section": 1,
                    "rotation_angle": 0.0,
                    "start_hinge": null,
                    "end_hinge": null,
                    "classification": "",
                    "weight": 26.668858682089727,
                    "chi": null,
                    "reference_member": null,
                    "reference_node": null,
                    "member_type": "Normal"
                }
            ]
        },
        {
            "id": 2,
            "l_y": null,
            "l_z": null,
            "classification": null,
            "members": [
                {
                    "id": 13,
                    "start_node": {
                        "id": 18,
                        "classification": "",
                        "X": 1.0,
                        "Y": 0.1,
                        "Z": -0.1,
                        "nodal_support": null
                    },
                    "end_node": {
                        "id": 17,
                        "classification": "",
                        "X": 1.0,
                        "Y": 0.1,
                        "Z": 0.0,
                        "nodal_support": 1
                    },
                    "section": 1,
                    "rotation_angle": 0.0,
                    "start_hinge": null,
                    "end_hinge": null,
                    "classification": "",
                    "weight": 2.222404890174144,
                    "chi": null,
                    "reference_member": null,
                    "reference_node": null,
                    "member_type": "Normal"
                },
                {
                    "id": 14,
                    "start_node": {
                        "id": 17,
                        "classification": "",
                        "X": 1.0,
                        "Y": 0.1,
                        "Z": 0.0,
                        "nodal_support": 1
                    },
                    "end_node": {
                        "id": 20,
                        "classification": "",
                        "X": 1.0,
                        "Y": 0.1,
                        "Z": 0.1,
                        "nodal_support": null
                    },
                    "section": 1,
                    "rotation_angle": 0.0,
                    "start_hinge": null,
                    "end_hinge": null,
                    "classification": "",
                    "weight": 2.222404890174144,
                    "chi": null,
                    "reference_member": null,
                    "reference_node": null,
                    "member_type": "Normal"
                },
                {
                    "id": 15,
                    "start_node": {
                        "id": 20,
                        "classification": "",
                        "X": 1.0,
                        "Y": 0.1,
                        "Z": 0.1,
                        "nodal_support": null
                    },
                    "end_node": {
                        "id": 19,
                        "classification": "",
                        "X": 1.0,
                        "Y": 0.1,
                        "Z": 1.3,
                        "nodal_support": 1
                    },
                    "section": 1,
                    "rotation_angle": 0.0,
                    "start_hinge": null,
                    "end_hinge": null,
                    "classification": "",
                    "weight": 26.668858682089727,
                    "chi": null,
                    "reference_member": null,
                    "reference_node": null,
                    "member_type": "Normal"
                }
            ]
        },
        {
            "id": 3,
            "l_y": null,
            "l_z": null,
            "classification": null,
            "members": [
                {
                    "id": 21,
                    "start_node": {
                        "id": 6,
                        "classification": "",
                        "X": 0.0,
                        "Y": 0.1,
                        "Z": 0.0,
                        "nodal_support": 1
                    },
                    "end_node": {
                        "id": 4,
                        "classification": "",
                        "X": 0.0,
                        "Y": 0.2,
                        "Z": 0.0,
                        "nodal_support": null
                    },
                    "section": null,
                    "rotation_angle": 0.0,
                    "start_hinge": null,
                    "end_hinge": null,
                    "classification": "",
                    "weight": 0.0,
                    "chi": null,
                    "reference_member": null,
                    "reference_node": null,
                    "member_type": "Rigid"
                },
                {
                    "id": 1,
                    "start_node": {
                        "id": 4,
                        "classification": "",
                        "X": 0.0,
                        "Y": 0.2,
                        "Z": 0.0,
                        "nodal_support": null
                    },
                    "end_node": {
                        "id": 3,
                        "classification": "",
                        "X": 0.0,
                        "Y": 0.5,
                        "Z": 0.0,
                        "nodal_support": null
                    },
                    "section": 1,
                    "rotation_angle": 0.0,
                    "start_hinge": 3,
                    "end_hinge": null,
                    "classification": "",
                    "weight": 6.667214670522432,
                    "chi": null,
                    "reference_member": null,
                    "reference_node": null,
                    "member_type": "Normal"
                },
                {
                    "id": 2,
                    "start_node": {
                        "id": 3,
                        "classification": "",
                        "X": 0.0,
                        "Y": 0.5,
                        "Z": 0.0,
                        "nodal_support": null
                    },
                    "end_node": {
                        "id": 2,
                        "classification": "",
                        "X": 0.0,
                        "Y": 2.0,
                        "Z": 0.0,
                        "nodal_support": null
                    },
                    "section": 1,
                    "rotation_angle": 0.0,
                    "start_hinge": null,
                    "end_hinge": null,
                    "classification": "",
                    "weight": 33.33607335261216,
                    "chi": null,
                    "reference_member": null,
                    "reference_node": null,
                    "member_type": "Normal"
                },
                {
                    "id": 3,
                    "start_node": {
                        "id": 2,
                        "classification": "",
                        "X": 0.0,
                        "Y": 2.0,
                        "Z": 0.0,
                        "nodal_support": null
                    },
                    "end_node": {
                        "id": 1,
                        "classification": "",
                        "X": 0.0,
                        "Y": 2.25,
                        "Z": 0.0,
                        "nodal_support": null
                    },
                    "section": 1,
                    "rotation_angle": 0.0,
                    "start_hinge": null,
                    "end_hinge": null,
                    "classification": "",
                    "weight": 5.55601222543536,
                    "chi": null,
                    "reference_member": null,
                    "reference_node": null,
                    "member_type": "Normal"
                },
                {
                    "id": 4,
                    "start_node": {
                        "id": 1,
                        "classification": "",
                        "X": 0.0,
                        "Y": 2.25,
                        "Z": 0.0,
                        "nodal_support": null
                    },
                    "end_node": {
                        "id": 5,
                        "classification": "",
                        "X": 0.0,
                        "Y": 2.5,
                        "Z": 0.0,
                        "nodal_support": null
                    },
                    "section": 1,
                    "rotation_angle": 0.0,
                    "start_hinge": null,
                    "end_hinge": null,
                    "classification": "",
                    "weight": 5.55601222543536,
                    "chi": null,
                    "reference_member": null,
                    "reference_node": null,
                    "member_type": "Normal"
                }
            ]
        },
        {
            "id": 4,
            "l_y": null,
            "l_z": null,
            "classification": null,
            "members": [
                {
                    "id": 24,
                    "start_node": {
                        "id": 17,
                        "classification": "",
                        "X": 1.0,
                        "Y": 0.1,
                        "Z": 0.0,
                        "nodal_support": 1
                    },
                    "end_node": {
                        "id": 15,
                        "classification": "",
                        "X": 1.0,
                        "Y": 0.2,
                        "Z": 0.0,
                        "nodal_support": null
                    },
                    "section": null,
                    "rotation_angle": 0.0,
                    "start_hinge": null,
                    "end_hinge": null,
                    "classification": "",
                    "weight": 0.0,
                    "chi": null,
                    "reference_member": null,
                    "reference_node": null,
                    "member_type": "Rigid"
                },
                {
                    "id": 9,
                    "start_node": {
                        "id": 15,
                        "classification": "",
                        "X": 1.0,
                        "Y": 0.2,
                        "Z": 0.0,
                        "nodal_support": null
                    },
                    "end_node": {
                        "id": 14,
                        "classification": "",
                        "X": 1.0,
                        "Y": 0.5,
                        "Z": 0.0,
                        "nodal_support": null
                    },
                    "section": 1,
                    "rotation_angle": 0.0,
                    "start_hinge": 3,
                    "end_hinge": null,
                    "classification": "",
                    "weight": 6.667214670522432,
                    "chi": null,
                    "reference_member": null,
                    "reference_node": null,
                    "member_type": "Normal"
                },
                {
                    "id": 10,
                    "start_node": {
                        "id": 14,
                        "classification": "",
                        "X": 1.0,
                        "Y": 0.5,
                        "Z": 0.0,
                        "nodal_support": null
                    },
                    "end_node": {
                        "id": 13,
                        "classification": "",
                        "X": 1.0,
                        "Y": 2.0,
                        "Z": 0.0,
                        "nodal_support": null
                    },
                    "section": 1,
                    "rotation_angle": 0.0,
                    "start_hinge": null,
                    "end_hinge": null,
                    "classification": "",
                    "weight": 33.33607335261216,
                    "chi": null,
                    "reference_member": null,
                    "reference_node": null,
                    "member_type": "Normal"
                },
                {
                    "id": 11,
                    "start_node": {
                        "id": 13,
                        "classification": "",
                        "X": 1.0,
                        "Y": 2.0,
                        "Z": 0.0,
                        "nodal_support": null
                    },
                    "end_node": {
                        "id": 12,
                        "classification": "",
                        "X": 1.0,
                        "Y": 2.25,
                        "Z": 0.0,
                        "nodal_support": null
                    },
                    "section": 1,
                    "rotation_angle": 0.0,
                    "start_hinge": null,
                    "end_hinge": null,
                    "classification": "",
                    "weight": 5.55601222543536,
                    "chi": null,
                    "reference_member": null,
                    "reference_node": null,
                    "member_type": "Normal"
                },
                {
                    "id": 12,
                    "start_node": {
                        "id": 12,
                        "classification": "",
                        "X": 1.0,
                        "Y": 2.25,
                        "Z": 0.0,
                        "nodal_support": null
                    },
                    "end_node": {
                        "id": 16,
                        "classification": "",
                        "X": 1.0,
                        "Y": 2.5,
                        "Z": 0.0,
                        "nodal_support": null
                    },
                    "section": 1,
                    "rotation_angle": 0.0,
                    "start_hinge": null,
                    "end_hinge": null,
                    "classification": "",
                    "weight": 5.55601222543536,
                    "chi": null,
                    "reference_member": null,
                    "reference_node": null,
                    "member_type": "Normal"
                }
            ]
        },
        {
            "id": 5,
            "l_y": null,
            "l_z": null,
            "classification": null,
            "members": [
                {
                    "id": 22,
                    "start_node": {
                        "id": 1,
                        "classification": "",
                        "X": 0.0,
                        "Y": 2.25,
                        "Z": 0.0,
                        "nodal_support": null
                    },
                    "end_node": {
                        "id": 10,
                        "classification": "",
                        "X": 0.0,
                        "Y": 2.25,
                        "Z": 0.1,
                        "nodal_support": null
                    },
                    "section": null,
                    "rotation_angle": 0.0,
                    "start_hinge": null,
                    "end_hinge": null,
                    "classification": "",
                    "weight": 0.0,
                    "chi": null,
                    "reference_member": null,
                    "reference_node": null,
                    "member_type": "Rigid"
                },
                {
                    "id": 8,
                    "start_node": {
                        "id": 10,
                        "classification": "",
                        "X": 0.0,
                        "Y": 2.25,
                        "Z": 0.1,
                        "nodal_support": null
                    },
                    "end_node": {
                        "id": 11,
                        "classification": "",
                        "X": 0.0,
                        "Y": 2.2814123370338706,
                        "Z": 1.2995887899951677,
                        "nodal_support": null
                    },
                    "section": 2,
                    "rotation_angle": 0.0,
                    "start_hinge": null,
                    "end_hinge": null,
                    "classification": "",
                    "weight": 9.665165568203943,
                    "chi": null,
                    "reference_member": null,
                    "reference_node": null,
                    "member_type": "Normal"
                }
            ]
        },
        {
            "id": 6,
            "l_y": null,
            "l_z": null,
            "classification": null,
            "members": [
                {
                    "id": 23,
                    "start_node": {
                        "id": 12,
                        "classification": "",
                        "X": 1.0,
                        "Y": 2.25,
                        "Z": 0.0,
                        "nodal_support": null
                    },
                    "end_node": {
                        "id": 21,
                        "classification": "",
                        "X": 1.0,
                        "Y": 2.25,
                        "Z": 0.1,
                        "nodal_support": null
                    },
                    "section": null,
                    "rotation_angle": 0.0,
                    "start_hinge": null,
                    "end_hinge": null,
                    "classification": "",
                    "weight": 0.0,
                    "chi": null,
                    "reference_member": null,
                    "reference_node": null,
                    "member_type": "Rigid"
                },
                {
                    "id": 16,
                    "start_node": {
                        "id": 21,
                        "classification": "",
                        "X": 1.0,
                        "Y": 2.25,
                        "Z": 0.1,
                        "nodal_support": null
                    },
                    "end_node": {
                        "id": 22,
                        "classification": "",
                        "X": 1.0,
                        "Y": 2.2814123370338706,
                        "Z": 1.2995887899951677,
                        "nodal_support": null
                    },
                    "section": 2,
                    "rotation_angle": 0.0,
                    "start_hinge": null,
                    "end_hinge": null,
                    "classification": "",
                    "weight": 9.665165568203943,
                    "chi": null,
                    "reference_member": null,
                    "reference_node": null,
                    "member_type": "Normal"
                }
            ]
        },
        {
            "id": 7,
            "l_y": null,
            "l_z": null,
            "classification": null,
            "members": [
                {
                    "id": 17,
                    "start_node": {
                        "id": 3,
                        "classification": "",
                        "X": 0.0,
                        "Y": 0.5,
                        "Z": 0.0,
                        "nodal_support": null
                    },
                    "end_node": {
                        "id": 14,
                        "classification": "",
                        "X": 1.0,
                        "Y": 0.5,
                        "Z": 0.0,
                        "nodal_support": null
                    },
                    "section": 3,
                    "rotation_angle": 0.0,
                    "start_hinge": 1,
                    "end_hinge": 1,
                    "classification": "",
                    "weight": 2.7542276346815,
                    "chi": null,
                    "reference_member": null,
                    "reference_node": null,
                    "member_type": "Normal"
                }
            ]
        },
        {
            "id": 8,
            "l_y": null,
            "l_z": null,
            "classification": null,
            "members": [
                {
                    "id": 18,
                    "start_node": {
                        "id": 2,
                        "classification": "",
                        "X": 0.0,
                        "Y": 2.0,
                        "Z": 0.0,
                        "nodal_support": null
                    },
                    "end_node": {
                        "id": 13,
                        "classification": "",
                        "X": 1.0,
                        "Y": 2.0,
                        "Z": 0.0,
                        "nodal_support": null
                    },
                    "section": 3,
                    "rotation_angle": 0.0,
                    "start_hinge": 1,
                    "end_hinge": 1,
                    "classification": "",
                    "weight": 2.7542276346815,
                    "chi": null,
                    "reference_member": null,
                    "reference_node": null,
                    "member_type": "Normal"
                }
            ]
        },
        {
            "id": 9,
            "l_y": null,
            "l_z": null,
            "classification": null,
            "members": [
                {
                    "id": 19,
                    "start_node": {
                        "id": 3,
                        "classification": "",
                        "X": 0.0,
                        "Y": 0.5,
                        "Z": 0.0,
                        "nodal_support": null
                    },
                    "end_node": {
                        "id": 13,
                        "classification": "",
                        "X": 1.0,
                        "Y": 2.0,
                        "Z": 0.0,
                        "nodal_support": null
                    },
                    "section": 5,
                    "rotation_angle": 0.0,
                    "start_hinge": 1,
                    "end_hinge": 1,
                    "classification": "",
                    "weight": 2.249863995889529,
                    "chi": null,
                    "reference_member": null,
                    "reference_node": null,
                    "member_type": "Tension"
                }
            ]
        },
        {
            "id": 10,
            "l_y": null,
            "l_z": null,
            "classification": null,
            "members": [
                {
                    "id": 20,
                    "start_node": {
                        "id": 2,
                        "classification": "",
                        "X": 0.0,
                        "Y": 2.0,
                        "Z": 0.0,
                        "nodal_support": null
                    },
                    "end_node": {
                        "id": 14,
                        "classification": "",
                        "X": 1.0,
                        "Y": 0.5,
                        "Z": 0.0,
                        "nodal_support": null
                    },
                    "section": 5,
                    "rotation_angle": 0.0,
                    "start_hinge": 1,
                    "end_hinge": 1,
                    "classification": "",
                    "weight": 2.249863995889529,
                    "chi": null,
                    "reference_member": null,
                    "reference_node": null,
                    "member_type": "Tension"
                }
            ]
        }
    ],
    "load_cases": [
        {
            "id": 1,
            "name": "Load Case DA",
            "nodal_loads": [],
            "nodal_moments": [],
            "distributed_loads": [
                {
                    "id": 1,
                    "member": 8,
                    "load_case": 1,
                    "distribution_shape": "Uniform",
                    "magnitude": 416.7,
                    "direction": [
                        1,
                        0,
                        0
                    ],
                    "start_frac": 0.0,
                    "end_frac": 1.0,
                    "end_magnitude": 416.7
                },
                {
                    "id": 2,
                    "member": 16,
                    "load_case": 1,
                    "distribution_shape": "Uniform",
                    "magnitude": 416.7,
                    "direction": [
                        1,
                        0,
                        0
                    ],
                    "start_frac": 0.0,
                    "end_frac": 1.0,
                    "end_magnitude": 416.7
                }
            ],
            "rotation_imperfections": [],
            "translation_imperfections": []
        }
    ],
    "load_combinations": [],
    "imperfection_cases": [],
    "settings": {
        "id": 1,
        "analysis_options": {
            "id": 1,
            "solve_loadcases": true,
            "solver": "newton_raphson",
            "tolerance": 0.01,
            "max_iterations": 30,
            "dimensionality": "3D",
            "order": "Nonlinear",
            "rigid_strategy": "LinearMpc"
        },
        "general_info": {
            "project_name": "Unnamed Project",
            "author": "Unknown",
            "version": "1.0"
        }
    },
    "memberhinges": [
        {
            "id": 3,
            "hinge_type": "Column base",
            "translational_release_vx": null,
            "translational_release_vy": null,
            "translational_release_vz": null,
            "rotational_release_mx": null,
            "rotational_release_my": null,
            "rotational_release_mz": 20344000,
            "max_tension_vx": null,
            "max_tension_vy": null,
            "max_tension_vz": null,
            "max_moment_mx": null,
            "max_moment_my": null,
            "max_moment_mz": null
        },
        {
            "id": 1,
            "hinge_type": "SPRING_YZ",
            "translational_release_vx": null,
            "translational_release_vy": null,
            "translational_release_vz": null,
            "rotational_release_mx": null,
            "rotational_release_my": 1000,
            "rotational_release_mz": 1000,
            "max_tension_vx": null,
            "max_tension_vy": null,
            "max_tension_vz": null,
            "max_moment_mx": null,
            "max_moment_my": null,
            "max_moment_mz": null
        }
    ],
    "materials": [
        {
            "id": 1,
            "name": "S235",
            "e_mod": 210000000000.0,
            "g_mod": 80769000000.0,
            "density": 7800,
            "yield_stress": 235000000.0
        }
    ],
    "sections": [
        {
            "id": 1,
            "name": "IPE 200 Beam Section",
            "material": 1,
            "h": 0.2,
            "b": 0.1,
            "i_y": 1.4237369185370059e-6,
            "i_z": 1.943796829178698e-5,
            "j": 6.910636270828207e-8,
            "area": 0.0028492370386848003,
            "shape_path": 1
        },
        {
            "id": 2,
            "name": "IPE 100 Beam Section",
            "material": 1,
            "h": 0.1,
            "b": 0.055,
            "i_y": 1.5919406165475848e-7,
            "i_z": 1.7106128520799252e-6,
            "j": 1.1669766129304922e-8,
            "area": 0.0010326031589961478,
            "shape_path": 2
        },
        {
            "id": 3,
            "name": "CFU",
            "material": 1,
            "h": 0.08,
            "b": 0.05,
            "i_y": 9.162909747785733e-8,
            "i_z": 3.789966265137473e-7,
            "j": 4.797323396675661e-10,
            "area": 0.00035310610701044874,
            "shape_path": 3
        },
        {
            "id": 5,
            "name": "FL 40x4x1.26",
            "material": 1,
            "h": null,
            "b": null,
            "i_y": 2.13e-10,
            "i_z": 2.1333e-8,
            "j": 0.08,
            "area": 0.00016,
            "shape_path": null
        }
    ],
    "nodal_supports": [
        {
            "id": 1,
            "classification": null,
            "displacement_conditions": {
                "X": {
                    "condition_type": "Fixed",
                    "stiffness": null
                },
                "Y": {
                    "condition_type": "Fixed",
                    "stiffness": null
                },
                "Z": {
                    "condition_type": "Fixed",
                    "stiffness": null
                }
            },
            "rotation_conditions": {
                "X": {
                    "condition_type": "Free",
                    "stiffness": null
                },
                "Y": {
                    "condition_type": "Free",
                    "stiffness": null
                },
                "Z": {
                    "condition_type": "Free",
                    "stiffness": null
                }
            }
        }
    ],
    "shape_paths": [
        {
            "id": 1,
            "name": "IPE 200 Beam Section",
            "shape_commands": [
                {
                    "command": "moveTo",
                    "y": 0.1,
                    "z": -0.05,
                    "r": null,
                    "center_y": null,
                    "center_z": null,
                    "theta0": null,
                    "theta1": null
                },
                {
                    "command": "lineTo",
                    "y": 0.1,
                    "z": 0.05,
                    "r": null,
                    "center_y": null,
                    "center_z": null,
                    "theta0": null,
                    "theta1": null
                },
                {
                    "command": "lineTo",
                    "y": 0.0915,
                    "z": 0.05,
                    "r": null,
                    "center_y": null,
                    "center_z": null,
                    "theta0": null,
                    "theta1": null
                },
                {
                    "command": "lineTo",
                    "y": 0.0915,
                    "z": 0.0148,
                    "r": null,
                    "center_y": null,
                    "center_z": null,
                    "theta0": null,
                    "theta1": null
                },
                {
                    "command": "arcTo",
                    "y": null,
                    "z": null,
                    "r": 0.012,
                    "center_y": 0.0795,
                    "center_z": 0.0148,
                    "theta0": 0.0,
                    "theta1": -1.5707963267948966
                },
                {
                    "command": "lineTo",
                    "y": -0.0795,
                    "z": 0.0028,
                    "r": null,
                    "center_y": null,
                    "center_z": null,
                    "theta0": null,
                    "theta1": null
                },
                {
                    "command": "arcTo",
                    "y": null,
                    "z": null,
                    "r": 0.012,
                    "center_y": -0.0795,
                    "center_z": 0.0148,
                    "theta0": -1.5707963267948966,
                    "theta1": -3.141592653589793
                },
                {
                    "command": "lineTo",
                    "y": -0.0915,
                    "z": 0.05,
                    "r": null,
                    "center_y": null,
                    "center_z": null,
                    "theta0": null,
                    "theta1": null
                },
                {
                    "command": "lineTo",
                    "y": -0.1,
                    "z": 0.05,
                    "r": null,
                    "center_y": null,
                    "center_z": null,
                    "theta0": null,
                    "theta1": null
                },
                {
                    "command": "lineTo",
                    "y": -0.1,
                    "z": -0.05,
                    "r": null,
                    "center_y": null,
                    "center_z": null,
                    "theta0": null,
                    "theta1": null
                },
                {
                    "command": "lineTo",
                    "y": -0.0915,
                    "z": -0.05,
                    "r": null,
                    "center_y": null,
                    "center_z": null,
                    "theta0": null,
                    "theta1": null
                },
                {
                    "command": "lineTo",
                    "y": -0.0915,
                    "z": -0.0148,
                    "r": null,
                    "center_y": null,
                    "center_z": null,
                    "theta0": null,
                    "theta1": null
                },
                {
                    "command": "arcTo",
                    "y": null,
                    "z": null,
                    "r": 0.012,
                    "center_y": -0.0795,
                    "center_z": -0.0148,
                    "theta0": 3.141592653589793,
                    "theta1": 1.5707963267948966
                },
                {
                    "command": "lineTo",
                    "y": 0.0795,
                    "z": -0.0028,
                    "r": null,
                    "center_y": null,
                    "center_z": null,
                    "theta0": null,
                    "theta1": null
                },
                {
                    "command": "arcTo",
                    "y": null,
                    "z": null,
                    "r": 0.012,
                    "center_y": 0.0795,
                    "center_z": -0.0148,
                    "theta0": 1.5707963267948966,
                    "theta1": 0
                },
                {
                    "command": "lineTo",
                    "y": 0.0915,
                    "z": -0.05,
                    "r": null,
                    "center_y": null,
                    "center_z": null,
                    "theta0": null,
                    "theta1": null
                },
                {
                    "command": "closePath",
                    "y": null,
                    "z": null,
                    "r": null,
                    "center_y": null,
                    "center_z": null,
                    "theta0": null,
                    "theta1": null
                }
            ]
        },
        {
            "id": 2,
            "name": "IPE 100 Beam Section",
            "shape_commands": [
                {
                    "command": "moveTo",
                    "y": 0.05,
                    "z": -0.0275,
                    "r": null,
                    "center_y": null,
                    "center_z": null,
                    "theta0": null,
                    "theta1": null
                },
                {
                    "command": "lineTo",
                    "y": 0.05,
                    "z": 0.0275,
                    "r": null,
                    "center_y": null,
                    "center_z": null,
                    "theta0": null,
                    "theta1": null
                },
                {
                    "command": "lineTo",
                    "y": 0.044300000000000006,
                    "z": 0.0275,
                    "r": null,
                    "center_y": null,
                    "center_z": null,
                    "theta0": null,
                    "theta1": null
                },
                {
                    "command": "lineTo",
                    "y": 0.044300000000000006,
                    "z": 0.00905,
                    "r": null,
                    "center_y": null,
                    "center_z": null,
                    "theta0": null,
                    "theta1": null
                },
                {
                    "command": "arcTo",
                    "y": null,
                    "z": null,
                    "r": 0.007,
                    "center_y": 0.03730000000000001,
                    "center_z": 0.00905,
                    "theta0": 0.0,
                    "theta1": -1.5707963267948966
                },
                {
                    "command": "lineTo",
                    "y": -0.03730000000000001,
                    "z": 0.00205,
                    "r": null,
                    "center_y": null,
                    "center_z": null,
                    "theta0": null,
                    "theta1": null
                },
                {
                    "command": "arcTo",
                    "y": null,
                    "z": null,
                    "r": 0.007,
                    "center_y": -0.03730000000000001,
                    "center_z": 0.00905,
                    "theta0": -1.5707963267948966,
                    "theta1": -3.141592653589793
                },
                {
                    "command": "lineTo",
                    "y": -0.044300000000000006,
                    "z": 0.0275,
                    "r": null,
                    "center_y": null,
                    "center_z": null,
                    "theta0": null,
                    "theta1": null
                },
                {
                    "command": "lineTo",
                    "y": -0.05,
                    "z": 0.0275,
                    "r": null,
                    "center_y": null,
                    "center_z": null,
                    "theta0": null,
                    "theta1": null
                },
                {
                    "command": "lineTo",
                    "y": -0.05,
                    "z": -0.0275,
                    "r": null,
                    "center_y": null,
                    "center_z": null,
                    "theta0": null,
                    "theta1": null
                },
                {
                    "command": "lineTo",
                    "y": -0.044300000000000006,
                    "z": -0.0275,
                    "r": null,
                    "center_y": null,
                    "center_z": null,
                    "theta0": null,
                    "theta1": null
                },
                {
                    "command": "lineTo",
                    "y": -0.044300000000000006,
                    "z": -0.00905,
                    "r": null,
                    "center_y": null,
                    "center_z": null,
                    "theta0": null,
                    "theta1": null
                },
                {
                    "command": "arcTo",
                    "y": null,
                    "z": null,
                    "r": 0.007,
                    "center_y": -0.03730000000000001,
                    "center_z": -0.00905,
                    "theta0": 3.141592653589793,
                    "theta1": 1.5707963267948966
                },
                {
                    "command": "lineTo",
                    "y": 0.03730000000000001,
                    "z": -0.00205,
                    "r": null,
                    "center_y": null,
                    "center_z": null,
                    "theta0": null,
                    "theta1": null
                },
                {
                    "command": "arcTo",
                    "y": null,
                    "z": null,
                    "r": 0.007,
                    "center_y": 0.03730000000000001,
                    "center_z": -0.00905,
                    "theta0": 1.5707963267948966,
                    "theta1": 0
                },
                {
                    "command": "lineTo",
                    "y": 0.044300000000000006,
                    "z": -0.0275,
                    "r": null,
                    "center_y": null,
                    "center_z": null,
                    "theta0": null,
                    "theta1": null
                },
                {
                    "command": "closePath",
                    "y": null,
                    "z": null,
                    "r": null,
                    "center_y": null,
                    "center_z": null,
                    "theta0": null,
                    "theta1": null
                }
            ]
        },
        {
            "id": 3,
            "name": "CFU",
            "shape_commands": [
                {
                    "command": "moveTo",
                    "y": 0.04,
                    "z": -0.025,
                    "r": null,
                    "center_y": null,
                    "center_z": null,
                    "theta0": null,
                    "theta1": null
                },
                {
                    "command": "lineTo",
                    "y": 0.04,
                    "z": 0.025,
                    "r": null,
                    "center_y": null,
                    "center_z": null,
                    "theta0": null,
                    "theta1": null
                },
                {
                    "command": "lineTo",
                    "y": 0.038,
                    "z": 0.025,
                    "r": null,
                    "center_y": null,
                    "center_z": null,
                    "theta0": null,
                    "theta1": null
                },
                {
                    "command": "lineTo",
                    "y": 0.038,
                    "z": -0.0214,
                    "r": null,
                    "center_y": null,
                    "center_z": null,
                    "theta0": null,
                    "theta1": null
                },
                {
                    "command": "arcTo",
                    "y": null,
                    "z": null,
                    "r": 0.0016,
                    "center_y": 0.0364,
                    "center_z": -0.0214,
                    "theta0": 0.0,
                    "theta1": -1.5707963267948966
                },
                {
                    "command": "lineTo",
                    "y": -0.0364,
                    "z": -0.023,
                    "r": null,
                    "center_y": null,
                    "center_z": null,
                    "theta0": null,
                    "theta1": null
                },
                {
                    "command": "arcTo",
                    "y": null,
                    "z": null,
                    "r": 0.0016,
                    "center_y": -0.0364,
                    "center_z": -0.0214,
                    "theta0": -1.5707963267948966,
                    "theta1": -3.141592653589793
                },
                {
                    "command": "lineTo",
                    "y": -0.038,
                    "z": 0.025,
                    "r": null,
                    "center_y": null,
                    "center_z": null,
                    "theta0": null,
                    "theta1": null
                },
                {
                    "command": "lineTo",
                    "y": -0.04,
                    "z": 0.025,
                    "r": null,
                    "center_y": null,
                    "center_z": null,
                    "theta0": null,
                    "theta1": null
                },
                {
                    "command": "lineTo",
                    "y": -0.04,
                    "z": -0.025,
                    "r": null,
                    "center_y": null,
                    "center_z": null,
                    "theta0": null,
                    "theta1": null
                },
                {
                    "command": "lineTo",
                    "y": 0.04,
                    "z": -0.025,
                    "r": null,
                    "center_y": null,
                    "center_z": null,
                    "theta0": null,
                    "theta1": null
                },
                {
                    "command": "closePath",
                    "y": null,
                    "z": null,
                    "r": null,
                    "center_y": null,
                    "center_z": null,
                    "theta0": null,
                    "theta1": null
                }
            ]
        }
    ],
    "resultsbundle": null
}