<?xml version='1.0' encoding='utf-8'?>
<vdex xmlns:xsi="http://www.w3.org/2001/XMLSchema-instance" xmlns="http://www.imsglobal.org/xsd/imsvdex_v1p0" language="en" orderSignificant="false" profileType="hierarchicalTokenTerms" xsi:schemaLocation="http://www.imsglobal.org/xsd/imsvdex_v1p0 imsvdex_v1p0.xsd http://www.imsglobal.org/xsd/imsmd_rootv1p2p1 imsmd_rootv1p2p1.xsd">
  <vocabName>
    <langstring language="en">DPSIR</langstring>
  </vocabName>
  <vocabIdentifier>dpsir</vocabIdentifier>
  <term>
    <termIdentifier>driving-forces</termIdentifier>
    <caption>
      <langstring language="en">Driving forces</langstring>
    </caption>
  </term>
  <term>
    <termIdentifier>impact</termIdentifier>
    <caption>
      <langstring language="en">Impact</langstring>
    </caption>
  </term>
  <term>
    <termIdentifier>pressure</termIdentifier>
    <caption>
      <langstring language="en">Pressure</langstring>
    </caption>
  </term>
  <term>
    <termIdentifier>response</termIdentifier>
    <caption>
      <langstring language="en">Response</langstring>
    </caption>
  </term>
  <term>
    <termIdentifier>state</termIdentifier>
    <caption>
      <langstring language="en">State</langstring>
    </caption>
  </term>
</vdex>